datatools/__init__.py
datatools/datatools.py
datatools_mikdowd-0.0.7.dist-info/LICENSE
datatools_mikdowd-0.0.7.dist-info/METADATA
datatools_mikdowd-0.0.7.dist-info/WHEEL
datatools_mikdowd-0.0.7.dist-info/top_level.txt
datatools_mikdowd-0.0.7.dist-info/RECORD
