Metadata-Version: 2.1
Name: datatools-mikdowd
Version: 0.0.7
Summary: datatools is a python package for doing basic data summaries and other tasks
Home-page: https://github.com/mdgis/datatools
Author: Michael Dowd
Author-email: mikdowd@gmail.com
License: MIT
Platform: UNKNOWN
Classifier: Development Status :: 4 - Beta
Classifier: License :: OSI Approved :: MIT License
Classifier: Programming Language :: Python
Classifier: Programming Language :: Python :: 3.5
Classifier: Programming Language :: Python :: 3.6
Classifier: Programming Language :: Python :: 3.7
Classifier: Topic :: Software Development :: Libraries
Classifier: Topic :: Software Development :: Libraries :: Python Modules
Classifier: Intended Audience :: Developers
Requires-Python: >=3.5
Requires-Dist: pandas
Requires-Dist: seaborn
